pyinsight_depositor_firestore/__init__.py
pyinsight_depositor_firestore/firestore_depositor.py
pyinsight_depositor_firestore-0.0.6.dist-info/LICENSE
pyinsight_depositor_firestore-0.0.6.dist-info/METADATA
pyinsight_depositor_firestore-0.0.6.dist-info/WHEEL
pyinsight_depositor_firestore-0.0.6.dist-info/top_level.txt
pyinsight_depositor_firestore-0.0.6.dist-info/RECORD
